zulip_bots/__init__.py
zulip_bots/bot_shell.py
zulip_bots/custom_exceptions.py
zulip_bots/finder.py
zulip_bots/game_handler.py
zulip_bots/lib.py
zulip_bots/provision.py
zulip_bots/py.typed
zulip_bots/request_test_lib.py
zulip_bots/run.py
zulip_bots/simple_lib.py
zulip_bots/test_file_utils.py
zulip_bots/test_lib.py
zulip_bots/bots/__init__.py
zulip_bots/bots/baremetrics/__init__.py
zulip_bots/bots/baremetrics/baremetrics.conf
zulip_bots/bots/baremetrics/baremetrics.py
zulip_bots/bots/baremetrics/doc.md
zulip_bots/bots/baremetrics/test_baremetrics.py
zulip_bots/bots/baremetrics/assets/list-commands.png
zulip_bots/bots/beeminder/__init__.py
zulip_bots/bots/beeminder/beeminder.conf
zulip_bots/bots/beeminder/beeminder.py
zulip_bots/bots/beeminder/doc.md
zulip_bots/bots/beeminder/test_beeminder.py
zulip_bots/bots/chessbot/__init__.py
zulip_bots/bots/chessbot/chess.conf
zulip_bots/bots/chessbot/chessbot.py
zulip_bots/bots/chessbot/doc.md
zulip_bots/bots/chessbot/test_chessbot.py
zulip_bots/bots/connect_four/__init__.py
zulip_bots/bots/connect_four/connect_four.py
zulip_bots/bots/connect_four/controller.py
zulip_bots/bots/connect_four/doc.md
zulip_bots/bots/connect_four/test_connect_four.py
zulip_bots/bots/converter/__init__.py
zulip_bots/bots/converter/converter.py
zulip_bots/bots/converter/doc.md
zulip_bots/bots/converter/test_converter.py
zulip_bots/bots/converter/utils.py
zulip_bots/bots/converter/assets/multiple-converts.png
zulip_bots/bots/define/__init__.py
zulip_bots/bots/define/define.py
zulip_bots/bots/define/doc.md
zulip_bots/bots/define/test_define.py
zulip_bots/bots/define/assets/correct_word.png
zulip_bots/bots/define/assets/wrong_word.png
zulip_bots/bots/dialogflow/__init__.py
zulip_bots/bots/dialogflow/dialogflow.conf
zulip_bots/bots/dialogflow/dialogflow.py
zulip_bots/bots/dialogflow/doc.md
zulip_bots/bots/dialogflow/test_dialogflow.py
zulip_bots/bots/dropbox_share/__init__.py
zulip_bots/bots/dropbox_share/doc.md
zulip_bots-0.9.0.dist-info/METADATA
zulip_bots-0.9.0.dist-info/WHEEL
zulip_bots-0.9.0.dist-info/entry_points.txt
zulip_bots-0.9.0.dist-info/top_level.txt
zulip_bots-0.9.0.dist-info/RECORD
