Metadata-Version: 2.1
Name: zulip-bots
Version: 0.9.0
Summary: Zulip's Bot framework
Home-page: https://www.zulip.org/
Author: Zulip Open Source Project
Author-email: zulip-devel@googlegroups.com
Project-URL: Source, https://github.com/zulip/python-zulip-api/
Project-URL: Documentation, https://zulip.com/api
Classifier: Development Status :: 4 - Beta
Classifier: Environment :: Web Environment
Classifier: Intended Audience :: Developers
Classifier: License :: OSI Approved :: Apache Software License
Classifier: Topic :: Communications :: Chat
Classifier: Programming Language :: Python :: 3
Classifier: Programming Language :: Python :: 3.8
Classifier: Programming Language :: Python :: 3.9
Classifier: Programming Language :: Python :: 3.10
Classifier: Programming Language :: Python :: 3.11
Requires-Python: >=3.8
Requires-Dist: pip
Requires-Dist: zulip
Requires-Dist: html2text
Requires-Dist: lxml
Requires-Dist: BeautifulSoup4
Requires-Dist: typing-extensions >=4.5.0
Requires-Dist: importlib-metadata >=3.6 ; python_version < "3.10"
